libreboundx.cpython-38-i386-linux-gnu.so
reboundx-4.1.0.dist-info/WHEEL
reboundx-4.1.0.dist-info/top_level.txt
reboundx-4.1.0.dist-info/LICENSE
reboundx-4.1.0.dist-info/RECORD
reboundx-4.1.0.dist-info/METADATA
reboundx/params.py
reboundx/__init__.py
reboundx/simulationarchive.py
reboundx/testing.py
reboundx/data.py
reboundx/extras.py
reboundx/constants.py
reboundx/tools.py
reboundx.libs/librebound-9a02641e.cpython-38-i386-linux-gnu.so
