Metadata-Version: 2.1
Name: reboundx
Version: 4.1.0
Summary: A library for including additional forces in REBOUND
Home-page: https://github.com/dtamayo/reboundx
Author: Daniel Tamayo
Author-email: dtamayo@hmc.edu
License: GPL
Keywords: astronomy astrophysics nbody integrator
Classifier: Development Status :: 5 - Production/Stable
Classifier: Intended Audience :: Science/Research
Classifier: Intended Audience :: Developers
Classifier: Topic :: Software Development :: Build Tools
Classifier: Topic :: Scientific/Engineering :: Astronomy
Classifier: License :: OSI Approved :: GNU General Public License v3 or later (GPLv3+)
Classifier: Programming Language :: Python :: 2
Classifier: Programming Language :: Python :: 3
License-File: LICENSE
Requires-Dist: rebound >=4.0.0
